Workbook

Sheet Concepts
A1: Status | B1: Praxis ID | C1: Canonical Name | D1: Tier | E1: Primary Domain | F1: Type | G1: Legacy Type | H1: Tradition | I1: Origin | J1: Date | K1: Difficulty | L1: Evidence | M1: One Sentence | N1: Story | O1: Definition | P1: Mechanism (ordered chain) | Q1: Common Misconception | R1: Nearest Neighbour | S1: Discriminate Scenario | T1: Praxis Exercise | U1: Identity Tags | V1: Related Concepts | W1: Book IDs | X1: Author | Y1: Notes
A2: Done | B2: 01.01 | C2: First Principles Thinking | D2: Integration | E2: Reasoning & Sensemaking | F2: Mental Model | G2: Mental Model | H2: Reasoning / Philosophy | I2: Rene Descartes | J2: 1637 | K2: Introductory | L2: Framework | M2: Break a problem down to what you know is true, then rebuild from there. | O2: Reasoning from foundational truths rather than by analogy to how things are already done. Descartes resolved to doubt everything he could and rebuild only on what survived the doubting. The move is to strip a problem back to the things you can actually defend, then reason forward from those alone. | P2: inherited assumption -> unexamined constraint -> only incremental improvement stripped to fundamentals -> constraints tested -> solutions convention was hiding | Q2: "It means ignoring what everyone else does." It does not require discarding convention. It requires knowing which parts of it are load-bearing. Most conventions encode a real constraint; the work is separating those from the ones that merely persist. | R2: CHESTERTON'S FENCE. That one warns you not to remove a convention until you understand why it exists. This one is the method for examining it. They pull in opposite directions and are strongest used together. | S2: A caterer prices every job at twice her ingredient cost, because that is what her old employer did. When a large order loses money she sits down and works out what actually drives her costs, and finds that labour, not ingredients, is the thing her pricing should have been tracking all along. | T2: STRIP IT DOWN 1. Name one rule you follow in your work. 2. Write down why you believe it is true. 3. For each reason ask: do I know this, or did I inherit it? 4. Keep only what you can defend, and rebuild the rule from those parts. COMMITMENT (if-then): "When I catch myself saying this is how it is done, I will write down what I actually know to be true before going further." | U2: Clear thinker | V2: Inversion | W2: BK030 | X2: Claude draft, needs Lindsay review
A3: Done | B3: 01.02 | C3: Inversion | D3: Integration | E3: Reasoning & Sensemaking | F3: Mental Model | G3: Mental Model | H3: Decision Theory / Practical Reasoning | I3: Carl Jacobi, popularised by Charlie Munger | J3: 2005 | K3: Introductory | L3: Framework | M3: Solve a problem backwards by asking what would guarantee failure. | O3: Rather than asking how to succeed, you ask how you would reliably fail, then remove those conditions. Attributed to the mathematician Carl Jacobi, who advised inverting difficult problems, and made a standing habit of thought by Charlie Munger. | P3: forward question -> vague aspirational answers -> nothing to act on inverted question -> concrete failure conditions -> specific behaviours to remove | Q3: "Inversion is just negative thinking." It is not pessimism. Failure conditions are simply easier to name precisely than success conditions, which is why inverting produces a list you can act on where the forward question produces platitudes. | R3: PREMORTEM. That one imagines a particular project has already failed and asks why. This is the general move of flipping any question on its head; the premortem is one applied instance of it. | S3: Tom wants to write a book and keeps making plans that go nowhere. A friend asks him instead to list everything he could do to make sure he never finishes it. He names four things straight away, realises he is already doing three of them, and stops one that week. | T3: FAILURE AUDIT 1. Choose one goal you currently care about. 2. Ask: how could I guarantee failure here? 3. List five behaviours that would make failure likely. 4. Mark the ones you are already doing. 5. Remove one of them this week. COMMITMENT (if-then): "When I set a goal, I will write the five ways I could guarantee failure before I write any plan." | U3: Clear thinker; Disciplined | V3: First Principles Thinking; Premortem | W3: BK059 | X3: Claude draft, needs Lindsay review
A4: Stub | B4: 01.03 | C4: Occam’s Razor | D4: Integration | E4: Reasoning & Sensemaking | F4: Heuristic | G4: Heuristic | H4: Philosophy of Science / Logic | U4: Clear thinker | W4: BK109
A5: Stub | B5: 01.04 | C5: Hanlon’s Razor | D5: Integration | E5: Reasoning & Sensemaking | F5: Heuristic | G5: Heuristic | H5: Practical Reasoning | U5: Clear thinker; Emotionally regulated | W5: BK096
A6: Stub | B6: 01.05 | C6: Chesterton’s Fence | D6: Integration | E6: Reasoning & Sensemaking | F6: Mental Model | G6: Mental Model | H6: Political Philosophy / Institutional Reasoning | U6: Clear thinker; High integrity | W6: BK120
A7: Stub | B7: 01.06 | C7: The Map Is Not the Territory | D7: Integration | E7: Reasoning & Sensemaking | F7: Mental Model | G7: Mental Model | H7: General Semantics / Epistemology | U7: Clear thinker | W7: BK067
A8: Stub | B8: 01.07 | C8: Falsifiability | D8: Integration | E8: Reasoning & Sensemaking | F8: Philosophical Principle | G8: Epistemic Principle | H8: Philosophy of Science | U8: Clear thinker | W8: BK003; BK109
A9: Stub | B9: 01.08 | C9: Burden of Proof | D9: Integration | E9: Reasoning & Sensemaking | F9: Influence Principle | G9: Argumentation Principle | H9: Logic / Argumentation | U9: Clear thinker; Manipulation proof | W9: BK087
A10: Done | B10: 01.09 | C10: Principle of Charity | D10: Integration | E10: Reasoning & Sensemaking | F10: Influence Principle | G10: Argumentation Principle | H10: Philosophy / Argumentation | I10: Neil Wilson and Donald Davidson | J10: 1959 | K10: Introductory | L10: Philosophical | M10: Interpreting what someone said in its strongest reasonable sense. | O10: A principle of interpretation holding that when a statement admits of several readings, you should engage the one that is most coherent and most likely to be meant. It is not generosity for its own sake. A weak reading of an argument tells you nothing about whether the argument is any good, so charity is a condition of learning anything from disagreement. | P10: you take the weakest available reading -> you refute something nobody argued -> you learn nothing and they do not change you take the strongest reading -> you engage the real claim -> either you are changed or they are | Q10: "Being charitable means agreeing more, or being soft on bad arguments." It makes criticism harder to escape, not softer. Refuting the strongest version is a far more serious challenge than refuting a sloppy one, and the person cannot reply that you misunderstood them. | R10: STEELMANNING. That goes a step further and improves the argument beyond what was actually said, constructing the best possible case. Charity stays within what the person plausibly meant. One is accurate interpretation, the other is active reconstruction. | S10: In a thread about remote work, someone writes that offices help junior staff. A reply treats this as a claim that everyone must return five days a week, and knocks it down easily. The original poster never meant that, and the exchange ends with both sides more certain than before. | T10: THE BEST READING 1. Find something you disagreed with this week, in writing. 2. Write the reading of it you reacted to. 3. Write the strongest reading it could bear. 4. Decide whether your objection still holds against the second one. COMMITMENT (if then): "When I am about to disagree in writing, I will write the strongest version of their point first and check my objection against that." | U10: Clear thinker; Clear communicator; High integrity | V10: Steelmanning; Straw Man Fallacy | W10: BK022 | X10: Claude draft, needs Lindsay review
A11: Done | B11: 01.10 | C11: Steelmanning | D11: Integration | E11: Reasoning & Sensemaking | F11: Influence Principle | G11: Argumentation Technique | H11: Argumentation / Debate | I11: Attributed to Daniel Dennett and others | J11: 2013 | K11: Intermediate | L11: Framework | M11: Building the strongest version of an argument before you take it apart. | O11: A practice of constructing the best case for a position, including improvements its actual defenders have not made, and then responding to that. Where charity asks you to read fairly, steelmanning asks you to build. Its purpose is partly honesty and partly self interest, because an objection that only defeats a weak version has told you nothing about whether you are right. | P11: you argue against what was said -> any weakness in their phrasing does your work for you -> your own position is never tested you argue against the strongest possible version -> their phrasing is no longer the weak point -> you find out whether you are actually right | Q11: "Steelmanning is a debate tactic for looking fair minded." If it is performed rather than done, it is worthless. The point is private, not social: you build the strong version in order to find out whether your own view survives it, and sometimes it does not. | R11: PRINCIPLE OF CHARITY. That asks you to interpret what was said in its strongest reasonable sense, staying within what the person meant. This goes beyond them, improving the argument past anything they said. Charity is about accuracy, this is about construction. | S11: Before writing a piece arguing against a popular productivity method, Nadia spends an afternoon writing the best case for it she can manage. Two of her four objections do not survive the exercise. The piece she eventually publishes makes the remaining two, and is far harder to dismiss. | T11: BUILD IT FIRST 1. Take a position you argue against. 2. Write the best case for it you can, including points its defenders usually miss. 3. Show it to someone who holds that view and ask what you left out. 4. Now write your objection, against that version. COMMITMENT (if then): "When I plan to argue against something publicly, I will write its strongest case first and check which of my objections survive." | U11: Clear thinker; Clear communicator | V11: Principle of Charity; Straw Man Fallacy | W11: BK022 | X11: Claude draft, needs Lindsay review
A12: Done | B12: 01.11 | C12: Straw Man Fallacy | D12: Integration | E12: Reasoning & Sensemaking | F12: Fallacy | G12: Fallacy | H12: Informal Logic | I12: Classical informal logic | K12: Introductory | L12: Philosophical | M12: Refuting a distorted version of an argument instead of the real one. | O12: An error of reasoning in which a position is restated in a weakened or exaggerated form, and the weakened form is then defeated. The appearance of victory comes from the substitution, not from the argument. It is often unintentional, since the distorted version is usually the one that felt easiest to answer. | P12: real claim is hard to answer -> a simpler version comes to mind -> the simpler version is attacked -> the original claim stands untouched | Q12: "A straw man is just any unfair characterisation of someone's view." Unfairness alone is not enough. The error is specifically substituting a weaker claim and then treating its defeat as a defeat of the original. Describing someone's view rudely but accurately is not this. | R12: MOTTE AND BAILEY. That is the mirror image, where a speaker defends a modest claim and then behaves as though a far bolder one had been established. One distorts the opponent's position downward, the other shifts one's own position back and forth. | S12: A councillor proposes reducing the speed limit on two residential streets. At the public meeting a resident stands up to say that banning cars from the town centre would destroy local business, and sits down to applause. The speed limit proposal is never discussed. | T12: FIND THE SUBSTITUTION 1. Recall an argument you felt you won easily. 2. Write what you argued against. 3. Write what they actually claimed, in their words if you have them. 4. If the two differ, your win was against something you built. COMMITMENT (if then): "When an opposing argument feels easy to defeat, I will check their actual words before replying." | U12: Clear thinker; Manipulation proof; Clear communicator | V12: Principle of Charity; Steelmanning | W12: BK014 | X12: Claude draft, needs Lindsay review
A13: Stub | B13: 01.12 | C13: Ad Hominem Fallacy | D13: Integration | E13: Reasoning & Sensemaking | F13: Fallacy | G13: Fallacy | H13: Informal Logic | U13: Clear thinker; Manipulation proof | W13: BK005
A14: Stub | B14: 01.13 | C14: False Dilemma | D14: Integration | E14: Reasoning & Sensemaking | F14: Fallacy | G14: Fallacy | H14: Informal Logic | U14: Clear thinker; Manipulation proof | W14: BK014
A15: Stub | B15: 01.14 | C15: Slippery Slope | D15: Integration | E15: Reasoning & Sensemaking | F15: Fallacy | G15: Fallacy | H15: Informal Logic | U15: Clear thinker; Manipulation proof | W15: BK070
A16: Stub | B16: 01.15 | C16: Appeal to Authority | D16: Integration | E16: Reasoning & Sensemaking | F16: Fallacy | G16: Fallacy | H16: Informal Logic / Epistemology | U16: Clear thinker; Manipulation proof | W16: BK008
A17: Stub | B17: 01.16 | C17: Appeal to Popularity | D17: Integration | E17: Reasoning & Sensemaking | F17: Fallacy | G17: Fallacy | H17: Informal Logic / Social Psychology | U17: Clear thinker; Manipulation proof | W17: BK121
A18: Stub | B18: 01.17 | C18: Appeal to Ignorance | D18: Integration | E18: Reasoning & Sensemaking | F18: Fallacy | G18: Fallacy | H18: Informal Logic | U18: Clear thinker; Manipulation proof | W18: BK010
A19: Stub | B19: 01.18 | C19: Circular Reasoning | D19: Integration | E19: Reasoning & Sensemaking | F19: Fallacy | G19: Fallacy | H19: Formal / Informal Logic | U19: Clear thinker; Manipulation proof | W19: BK015
A20: Stub | B20: 01.19 | C20: Red Herring | D20: Integration | E20: Reasoning & Sensemaking | F20: Fallacy | G20: Fallacy | H20: Argumentation / Rhetoric | U20: Clear thinker; Manipulation proof | W20: BK087
A21: Stub | B21: 01.20 | C21: Equivocation | D21: Integration | E21: Reasoning & Sensemaking | F21: Fallacy | G21: Fallacy | H21: Logic / Linguistics | U21: Clear thinker; Manipulation proof | W21: BK044
A22: Stub | B22: 01.21 | C22: Genetic Fallacy | D22: Integration | E22: Reasoning & Sensemaking | F22: Fallacy | G22: Fallacy | H22: Informal Logic | U22: Clear thinker; Manipulation proof | W22: BK014
A23: Stub | B23: 01.22 | C23: No True Scotsman | D23: Integration | E23: Reasoning & Sensemaking | F23: Fallacy | G23: Fallacy | H23: Informal Logic | U23: Clear thinker; Manipulation proof | W23: BK127
A24: Stub | B24: 01.23 | C24: Moving the Goalposts | D24: Integration | E24: Reasoning & Sensemaking | F24: Fallacy | G24: Fallacy | H24: Argumentation | U24: Clear thinker; Manipulation proof | W24: BK011
... A31: Stub | B31: 02.05 | C31: Base-Rate Neglect | D31: Integration | E31: Decisions & Risk | F31: Cognitive Bias | G31: Cognitive Bias | H31: Cognitive Psychology / Behavioral Decision Science | U31: Sound judgement | W31: BK061; BK128
A32: Done | B32: 02.06 | C32: Sunk-Cost Fallacy | D32: Integration | E32: Decisions & Risk | F32: Cognitive Bias | G32: Cognitive Bias | H32: Behavioral Economics / Decision Science | I32: Hal Arkes and Catherine Blumer | J32: 1985 | K32: Introductory | L32: Replicated | M32: Carrying on with something because of what you already spent on it. | O32: A sunk cost is a cost already paid that cannot be recovered. The fallacy is letting it influence a decision about the future. Rationally, only the costs and benefits still ahead of you should count; in practice, what has already gone in exerts a strong pull toward continuing. | P32: resources already committed -> continuing feels like recovering them -> quitting feels like admitting waste -> the decision is made on the past rather than the future | Q32: "It means you should quit things easily." It does not. Plenty of commitments are worth continuing on their own merits. The fallacy is specifically about using past expenditure as the reason, rather than whether the thing is still worth doing from here. | R32: LOSS AVERSION. That one is the general tendency to feel losses more sharply than equivalent gains. Sunk cost is a specific decision error that loss aversion helps explain. You can be loss averse without committing the fallacy, and the fallacy also draws on a reluctance to look inconsistent. | S32: Elena is two years into a qualification she no longer wants, in a field she has decided against. Every time she considers stopping, she thinks about the fees and the evenings already spent. She signs up for another year, and cannot say what the qualification will actually get her. | T32: THE FRESH START TEST 1. Name a commitment you are unsure about. 2. Ask: if I were arriving at this today, with none of the history, would I choose it? 3. If no, write what is actually keeping you in it. 4. Separate the reasons that look forward from the ones that look back. COMMITMENT (if-then): "When I notice I am justifying something by what I have already put in, I will ask what I would choose if I were starting from today." | U32: Sound judgement; Disciplined | V32: Loss Aversion; Opportunity Cost | W32: BK026; BK061 | X32: Claude draft, needs Lindsay review
A33: Stub | B33: 02.07 | C33: Loss Aversion | D33: Integration | E33: Decisions & Risk | F33: Cognitive Bias | G33: Cognitive Bias | H33: Behavioral Economics | U33: Sound judgement; Emotionally regulated | W33: BK061
A34: Stub | B34: 02.08 | C34: Anchoring | D34: Integration | E34: Decisions & Risk | F34: Cognitive Bias | G34: Cognitive Bias | H34: Behavioral Economics / Cognitive Psychology | U34: Sound judgement; Manipulation proof | W34: BK061
A35: Stub | B35: 02.09 | C35: Framing Effect | D35: Integration | E35: Decisions & Risk | F35: Cognitive Bias | G35: Cognitive Bias | H35: Behavioral Economics / Cognitive Psychology | U35: Sound judgement; Manipulation proof | W35: BK026; BK061
A36: Stub | B36: 02.10 | C36: Availability Heuristic | D36: Integration | E36: Decisions & Risk | F36: Cognitive Bias | G36: Heuristic / Bias | H36: Cognitive Psychology | U36: Sound judgement | W36: BK128
A37: Stub | B37: 02.11 | C37: Representativeness Heuristic | D37: Integration | E37: Decisions & Risk | F37: Cognitive Bias | G37: Heuristic / Bias | H37: Cognitive Psychology | U37: Sound judgement | W37: BK128
A38: Stub | B38: 02.12 | C38: Status-Quo Bias | D38: Integration | E38: Decisions & Risk | F38: Cognitive Bias | G38: Cognitive Bias | H38: Behavioral Economics | U38: Sound judgement; Disciplined | W38: BK026; BK061
A39: Stub | B39: 02.13 | C39: Endowment Effect | D39: Integration | E39: Decisions & Risk | F39: Cognitive Bias | G39: Cognitive Bias | H39: Behavioral Economics | U39: Sound judgement | W39: BK061
A40: Stub | B40: 02.14 | C40: Survivorship Bias | D40: Integration | E40: Decisions & Risk | F40: Cognitive Bias | G40: Cognitive Bias | H40: Decision Science / Statistics | U40: Sound judgement | W40: BK007; BK128
A41: Stub | B41: 02.15 | C41: Present Bias | D41: Integration | E41: Decisions & Risk | F41: Cognitive Bias | G41: Cognitive Bias | H41: Behavioral Economics / Decision Science | U41: Disciplined; Self-authoring | W41: BK012; BK061
A42: Stub | B42: 02.16 | C42: Affect Heuristic | D42: Integration | E42: Decisions & Risk | F42: Cognitive Bias | G42: Heuristic / Bias | H42: Cognitive Psychology / Risk Perception | U42: Sound judgement; Emotionally regulated | W42: BK128
A43: Stub | B43: 02.17 | C43: Outcome Bias | D43: Integration | E43: Decisions & Risk | F43: Cognitive Bias | G43: Cognitive Bias | H43: Decision Science | U43: Sound judgement | W43: BK128
A44: Stub | B44: 02.18 | C44: Hindsight Bias | D44: Integration | E44: Decisions & Risk | F44: Cognitive Bias | G44: Cognitive Bias | H44: Cognitive Psychology / Decision Science | U44: Sound judgement | W44: BK128
... A63: Stub | B63: 03.12 | C63: Rationalization | D63: Integration | E63: Self-Knowledge & Behaviour | F63: Defense Mechanism | G63: Defense Mechanism | H63: Psychodynamic Psychology / Social Psychology | U63: Self-authoring; Clear thinker | W63: BK090; BK099
A64: Done | B64: 03.13 | C64: Solomon’s Paradox | D64: Integration | E64: Self-Knowledge & Behaviour | F64: Paradox | G64: Psychological Effect / Paradox | H64: Social Psychology / Wisdom Research | I64: Igor Grossmann and Ethan Kross | J64: 2014 | K64: Introductory | L64: Supported | M64: We reason more wisely about other people's problems than our own. | O64: Named for King Solomon, who counselled others wisely but governed his own household badly. Grossmann and Kross found that people reason about their own problems with measurably less wisdom, by which is meant acknowledging the limits of what they know, allowing for change, weighing other perspectives and seeking compromise, than about an identical problem belonging to someone else. | P64: my problem -> high emotional proximity -> narrowed perspective -> poorer reasoning someone else's problem -> psychological distance -> broader perspective -> wiser reasoning | Q64: "People are just smarter about other people's lives." The effect is not about intelligence, and not about caring less. The same person, with the same intelligence, reasons worse on their own problem. The variable is distance, not ability, which is why manufacturing distance artificially reverses the effect. | R64: ACTOR-OBSERVER BIAS. That one is about attribution: we explain our own behaviour by circumstance and other people's by character. This is about the quality of reasoning itself, not about who gets blamed. A person can show either one without the other. | S64: Maya tells her friend, without hesitating, that she should leave a relationship in which she is constantly let down. Six months later Maya is in a near-identical situation and finds herself explaining why this time the circumstances are different, and why leaving now would be premature. | T64: THE OUTSIDER TEST 1. Choose one unresolved problem currently affecting you. 2. Write it in the third person: "[Name] has been struggling with..." 3. Answer as though advising your closest friend: - What would you tell her? - What is she failing to see? - What is she treating as certain that is not? - Whose perspective has she not considered? - What might look different in six months? 4. Return to the first person: what advice still applies to you? COMMITMENT (if-then): "When I notice I am emotionally invested in a decision, I will write the problem in the third person before deciding anything." | U64: Clear thinker; Self-authoring; Emotionally regulated | V64: Actor Observer Bias; Cognitive Reappraisal | W64: BK019 | X64: Claude draft, needs Lindsay review
A65: Stub | B65: 03.14 | C65: Psychological Reactance | D65: Integration | E65: Self-Knowledge & Behaviour | F65: Psychological Effect | G65: Psychological Effect | H65: Social Psychology | U65: Self-authoring; Manipulation proof | W65: BK039; BK085
A66: Stub | B66: 03.15 | C66: Self-Determination Theory | D66: Discovery | E66: Self-Knowledge & Behaviour | F66: Motivation Theory | G66: Motivation Theory | H66: Motivational Psychology | U66: Self-authoring; Disciplined | W66: BK031; BK052
A67: Stub | B67: 03.16 | C67: Implementation Intentions | D67: Integration | E67: Self-Knowledge & Behaviour | F67: Behavioural Principle | G67: Behavior-Change Technique | H67: Behavioral Psychology | U67: Disciplined; Self-authoring | W67: BK012
A68: Stub | B68: 03.17 | C68: Commitment Devices | D68: Integration | E68: Self-Knowledge & Behaviour | F68: Behavioural Principle | G68: Behavior-Change Technique | H68: Behavioral Economics / Self-Regulation | U68: Disciplined | W68: BK012; BK029
A69: Stub | B69: 03.18 | C69: Four Stages of Habit Formation | D69: Integration | E69: Self-Knowledge & Behaviour | F69: Behavioural Principle | G69: Behavioral Model | H69: Behavior Design / Behavioral Psychology | U69: Disciplined | W69: BK012
A70: Stub | B70: 03.19 | C70: Friction & Environment Design | D70: Integration | E70: Self-Knowledge & Behaviour | F70: Behavioural Principle | G70: Behavioral Principle | H70: Behavior Design / Behavioral Economics | U70: Disciplined | W70: BK012
A71: Stub | B71: 03.20 | C71: Hedonic Adaptation | D71: Integration | E71: Self-Knowledge & Behaviour | F71: Psychological Effect | G71: Psychological Effect | H71: Positive Psychology / Behavioral Science | U71: Self-authoring; Emotionally regulated | W71: BK102
A72: Stub | B72: 03.21 | C72: Affective Forecasting | D72: Integration | E72: Self-Knowledge & Behaviour | F72: Psychological Effect | G72: Psychological Effect | H72: Social Psychology / Decision Science | U72: Self-authoring; Clear thinker | W72: BK061
A73: Stub | B73: 03.22 | C73: Emotional Granularity | D73: Integration | E73: Self-Knowledge & Behaviour | F73: Psychological Effect | G73: Psychological Skill | H73: Affective Science | U73: Emotionally regulated | W73: BK032
A74: Stub | B74: 03.23 | C74: Cognitive Reappraisal | D74: Integration | E74: Self-Knowledge & Behaviour | F74: Strategic Principle | G74: Emotion-Regulation Strategy | H74: Affective Science / Cognitive Psychology | U74: Emotionally regulated | W74: BK032; BK053
A75: Stub | B75: 03.24 | C75: Experiential Avoidance | D75: Integration | E75: Self-Knowledge & Behaviour | F75: Psychological Effect | G75: Psychological Process | H75: Acceptance & Commitment Therapy | U75: Emotionally regulated; Self-authoring | W75: BK043; BK102
A76: Stub | B76: 03.25 | C76: Psychological Flexibility | D76: Integration | E76: Self-Knowledge & Behaviour | F76: Psychological Effect | G76: Psychological Process | H76: Acceptance & Commitment Therapy | U76: Emotionally regulated; Self-authoring | W76: BK102; BK124
... A120: Stub | B120: 05.19 | C120: Repair Attempts | D120: Integration | E120: Relationships & Attraction | F120: Relationship Pattern | G120: Relationship Concept | H120: Relationship Research | U120: Emotionally regulated; Clear communicator | W120: BK114
A121: Done | B121: 05.20 | C121: Gottman’s Four Horsemen | D121: Integration | E121: Relationships & Attraction | F121: Relationship Pattern | G121: Relationship Framework | H121: Relationship Research | I121: John Gottman | J121: 1994 | K121: Introductory | L121: Contested | M121: Four patterns in conflict that predict a relationship is in trouble. | O121: Gottman's observational work identified four communication patterns that reliably predict relationship breakdown: criticism, which attacks character rather than behaviour, contempt, which conveys superiority, defensiveness, which deflects responsibility, and stonewalling, which withdraws from the exchange altogether. Contempt was the strongest single predictor. | P121: complaint about behaviour -> criticism of character -> contempt -> the partner defends -> one of them withdraws -> the cycle repeats with nothing addressed | Q121: "Gottman can predict divorce with over ninety per cent accuracy." That figure comes from models fitted to couples whose outcomes were already known, which is a much weaker thing than predicting an unknown future, and independent attempts to reproduce it have not matched it. The four behaviours are real and worth knowing. The accuracy claim attached to them is not settled. | R121: DEMAND WITHDRAW PATTERN. That is one specific cycle where one partner pursues and the other retreats, and it maps closely onto two of the four, criticism and stonewalling. The four horsemen are a wider set of markers rather than a single interactional loop. | S121: Every time the finances come up, one of them starts with you never and the other starts with well you are the one who. Within four minutes one has stopped responding and is looking at their phone. They have had this exact exchange perhaps thirty times and have never once discussed the actual budget. | T121: SPOT YOUR OWN 1. Recall your last difficult conversation with someone close. 2. Of the four, which one did you supply? Be specific about the sentence. 3. Write what the behaviour based version of that sentence would have been. 4. Use it next time the subject arises. COMMITMENT (if then): "When I catch myself starting a sentence with you always or you never, I will stop and name the specific behaviour instead." | U121: Emotionally regulated; Clear communicator; High integrity | V121: Nonviolent Communication Framework; Demand-Withdraw Pattern | W121: BK133 | X121: Claude draft, needs Lindsay review
A122: Stub | B122: 05.21 | C122: Demand-Withdraw Pattern | D122: Integration | E122: Relationships & Attraction | F122: Relationship Pattern | G122: Relationship Pattern | H122: Relationship Research / Communication | U122: Emotionally regulated; Clear communicator | W122: BK013; BK022
A123: Stub | B123: 05.22 | C123: Active Constructive Responding | D123: Integration | E123: Relationships & Attraction | F123: Practice | G123: Relationship Practice | H123: Positive Psychology | U123: Emotionally regulated; Clear communicator | W123: BK033
A124: Stub | B124: 05.23 | C124: Reciprocal Self Disclosure | D124: Integration | E124: Relationships & Attraction | F124: Relationship Pattern | G124: Relationship Dynamic | H124: Social Psychology / Relationship Science | U124: Clear communicator; High integrity | W124: BK018; BK055
A125: Stub | B125: 05.24 | C125: Communal vs. Exchange Relationships | D125: Discovery | E125: Relationships & Attraction | F125: Relationship Pattern | G125: Relationship Model | H125: Social Psychology | U125: High integrity | W125: BK036
A126: Stub | B126: 05.25 | C126: Michelangelo Phenomenon | D126: Discovery | E126: Relationships & Attraction | F126: Relationship Pattern | G126: Relationship Effect | H126: Social Psychology / Relationship Science | U126: Emotionally regulated; High integrity | W126: BK077
A127: Done | B127: 06.01 | C127: Active Listening | D127: Integration | E127: Communication & Influence | F127: Practice | G127: Communication Practice | H127: Communication Studies / Counseling | I127: Carl Rogers and Richard Farson | J127: 1957 | K127: Introductory | L127: Supported | M127: Listening to understand the person rather than to prepare your reply. | O127: A practice in which the listener's whole attention goes to building an accurate picture of what the speaker means, and the speaker can see that happening. It involves not interrupting, not rehearsing a response while the other person talks, and checking your understanding out loud before responding to it. Rogers and Farson set it out as a working method rather than a personality trait. | P127: attention on your own reply -> you hear only the parts you can answer -> the speaker feels processed attention on their meaning -> you hear the whole thing -> the speaker feels understood and says more | Q127: "Active listening means nodding and saying mm hmm." Those are signals, not the practice. A person can nod continuously while composing their rebuttal. The practice is the internal act of trying to build their meaning rather than your answer, and the signals only matter if that is actually happening. | R127: REFLECTIVE LISTENING. That is one technique inside this practice, where you say back what you understood. Active listening is the wider posture of attending to meaning first, which can be shown in many ways besides reflecting. | S127: Priya's colleague starts describing a problem with the schedule. Twenty seconds in, Priya has the answer and is waiting for a pause to say it. She delivers a good solution. Her colleague thanks her, and does not mention the part he had not got to yet, which was the actual difficulty. | T127: THE NO REPLY MINUTE 1. Choose one conversation today that matters. 2. For the first minute, do not plan any part of your response. 3. When they pause, say what you understood before you say anything else. 4. Note afterwards: did they add something they had not said yet? COMMITMENT (if then): "When someone brings me a problem, I will say back what I understood before I offer anything." | U127: Clear communicator; Emotionally regulated | V127: Reflective Listening; Open Ended Questions | W127: BK022; BK103 | X127: Claude draft, needs Lindsay review
A128: Done | B128: 06.02 | C128: Reflective Listening | D128: Integration | E128: Communication & Influence | F128: Practice | G128: Communication Practice | H128: Counseling / Communication | I128: Carl Rogers | J128: 1951 | K128: Introductory | L128: Supported | M128: Saying back what you understood, so the speaker can correct you. | O128: A technique in which the listener restates the speaker's meaning in their own words and invites correction. Its value is not politeness. It converts a private, unverified guess about what someone meant into something they can confirm or fix, which is the only way to know whether you understood. | P128: you form a private interpretation -> it is never tested -> you respond to the wrong thing you say the interpretation out loud -> they confirm or correct it -> you respond to what they meant | Q128: "It means repeating their words back to them." Repeating the words proves nothing, since you can parrot a sentence you have not understood. It has to be in your own words, because the act of rephrasing is what exposes whether you actually got it. | R128: ACTIVE LISTENING. That is the wider practice of attending to meaning rather than to your reply. This is one specific move inside it, and you can do this move badly while listening well, or do it mechanically while listening poorly. | S128: A client writes a long message about wanting things to move faster. Tom replies with a revised timeline. She writes back that speed was not really the issue, it was that she had not known where things stood. Tom had solved the problem he recognised rather than the one she had. | T128: SAY IT BACK 1. Pick a conversation where you and the other person keep missing each other. 2. Before responding, say: so what I am hearing is, and then put their point in your own words. 3. Ask whether that is right. 4. Write down what they corrected. That difference is what you had been answering. COMMITMENT (if then): "When a conversation feels like it is going in circles, I will restate their point in my own words and ask if I have it." | U128: Clear communicator; Emotionally regulated | V128: Active Listening | W128: BK022; BK103 | X128: Claude draft, needs Lindsay review
A129: Stub | B129: 06.03 | C129: Behavioral Mimicry | D129: Discovery | E129: Communication & Influence | F129: Psychological Effect | G129: Psychological Effect | H129: Social Psychology / Nonverbal Communication | U129: Clear communicator; Manipulation proof | W129: BK018; BK103
A130: Done | B130: 06.04 | C130: Affect Labeling | D130: Integration | E130: Communication & Influence | F130: Communication Principle | G130: Communication / Emotion Technique | H130: Affective Science / Communication | I130: Matthew Lieberman | J130: 2007 | K130: Introductory | L130: Replicated | M130: Naming an emotion out loud reduces its intensity. | O130: Putting a feeling into words measurably lowers its grip, in yourself and in the person you are speaking to. Lieberman's imaging work found that labelling an emotion reduced activity in the amygdala and raised it in regions associated with deliberate control. In conversation it means naming what the other person appears to feel rather than arguing with it. | P130: feeling goes unnamed -> it stays diffuse and large -> it drives the conversation feeling is named plainly -> it becomes a specific thing on the table -> it can be discussed instead of acted out | Q130: "You are telling people how they feel." The move is tentative, not declarative. It is closer to it sounds like this has been frustrating than to you are frustrated. Getting it slightly wrong still works, because the person corrects you and has now named it themselves. | R130: COGNITIVE REAPPRAISAL. That one changes how you interpret a situation in order to change the feeling. This one does not reinterpret anything. It simply names the feeling as it is, and the naming alone does the work. | S130: A customer has been escalating for ten minutes. Instead of restating the refund policy again, the agent says it sounds like the worst part was being passed between three people. The customer stops, agrees, and the volume drops. Nothing about the policy has changed. | T130: NAME IT FIRST 1. Choose a conversation you expect to be tense. 2. Before addressing the content, name what the other person seems to be feeling, tentatively. 3. Let them correct you if you are off. 4. Only then move to the substance. COMMITMENT (if then): "When someone is clearly upset, I will name what they seem to be feeling before I address the facts." | U130: Clear communicator; Emotionally regulated | V130: Nonviolent Communication Framework; Reflective Listening | W130: BK022 | X130: Claude draft, needs Lindsay review
A131: Done | B131: 06.05 | C131: Open Ended Questions | D131: Integration | E131: Communication & Influence | F131: Communication Principle | G131: Communication Technique | H131: Communication / Counseling | I131: Standard interviewing and counselling practice | K131: Introductory | L131: Framework | M131: Questions that cannot be answered yes or no, so the other person chooses what matters. | O131: A question built so the answer has to be constructed rather than selected. Closed questions test a hypothesis you already have. Open questions hand the choice of direction to the other person, which is how you find out the thing you did not know to ask about. | P131: closed question -> they confirm or deny your guess -> you learn only about your guess open question -> they decide what is relevant -> you learn what you did not know to ask | Q131: "Open questions are just longer questions." Length has nothing to do with it. Tell me more is open and short. Did the delay frustrate you is closed and long. What makes a question open is whether the shape of the answer is already decided by the asker. | R131: ELABORATIVE INTERROGATION. That is a study technique where you ask yourself why a fact is true in order to remember it. This is a conversational move aimed at another person, with the purpose of discovery rather than retention. | S131: A manager asks each person leaving the company whether they were happy with their pay. Almost all say yes, and she concludes pay is not the problem. She never finds out that three of them left because of the same colleague, because nothing she asked left room for it. | T131: THE QUESTION SWAP 1. Write the three questions you plan to ask in your next important conversation. 2. For each, ask whether you could answer it yourself with a guess. 3. If you could, rewrite it so you could not. 4. Ask the rewritten versions. COMMITMENT (if then): "When I prepare questions for a conversation that matters, I will rewrite any I could already guess the answer to." | U131: Clear communicator | V131: Active Listening; Common Ground in Conversation | W131: BK022; BK103 | X131: Claude draft, needs Lindsay review
A132: Done | B132: 06.06 | C132: Grice’s Cooperative Principle | D132: Discovery | E132: Communication & Influence | F132: Communication Principle | G132: Communication Principle | H132: Pragmatics / Linguistics | I132: Paul Grice | J132: 1975 | K132: Intermediate | L132: Philosophical | M132: Conversation runs on an unspoken agreement to be informative, truthful, relevant and clear. | O132: Grice proposed that conversation is governed by a cooperative principle and four maxims: say enough but not too much, say what you believe true, say what is relevant, and say it clearly. The maxims are not rules people obey. They are expectations that let a listener work out what is meant from what is said, including when a maxim is deliberately broken. | P132: listener assumes the speaker is cooperating -> speaker says something that seems to break a maxim -> listener infers the meaning that would restore cooperation -> more is communicated than was said | Q132: "The maxims are rules for how to speak well." Grice was describing how understanding works, not giving advice. The interesting cases are the ones where a maxim is flouted on purpose, since that is precisely how sarcasm, understatement and implication carry meaning. | R132: CONVERSATIONAL IMPLICATURE. That is the meaning a listener derives beyond the literal words. This is the underlying account that explains why the derivation is possible at all. One is the mechanism, the other is its output. | S132: Asked for a reference, a professor writes only that the candidate has excellent handwriting and was always punctual. Every word is true and nothing negative is stated. The committee understands the letter perfectly, and the candidate is not shortlisted. | U132: Clear communicator | V132: Conversational Implicature; Common Ground in Conversation | W132: BK044 | X132: Claude draft, needs Lindsay review
A133: Stub | B133: 06.07 | C133: Conversational Implicature | D133: Discovery | E133: Communication & Influence | F133: Communication Principle | G133: Linguistic Concept | H133: Pragmatics / Linguistics | U133: Clear communicator | W133: BK044
A134: Stub | B134: 06.08 | C134: Speech Act Theory | D134: Discovery | E134: Communication & Influence | F134: Communication Principle | G134: Linguistic Theory | H134: Pragmatics / Philosophy of Language | U134: Clear communicator | W134: BK044
A135: Done | B135: 06.09 | C135: Common Ground in Conversation | D135: Integration | E135: Communication & Influence | F135: Communication Principle | G135: Communication Concept | H135: Psycholinguistics / Communication | I135: Herbert Clark | J135: 1996 | K135: Intermediate | L135: Supported | M135: Conversation works by building a shared store of what both people already know. | O135: Clark's account of conversation as a joint activity, in which participants continuously track what they can assume the other already knows. Every reference to a previous point, every shorthand, every it or that draws on this store. Where the store is thin, speakers must spell more out; where it is thick, a few words carry a great deal. | P135: speaker assumes shared ground that is not there -> listener loses the referent -> the thread breaks silently speaker checks the ground first -> references land -> short phrases carry full meaning | Q135: "It means finding things you have in common." That is rapport, which is a different thing. Common ground here is strictly about what each person can assume the other already knows, and two people with nothing in common can build plenty of it over one careful conversation. | R135: CURSE OF KNOWLEDGE. That is the bias that makes you unable to imagine not knowing what you know. This is the mechanism it damages: common ground is the thing being misjudged, and the curse is why the misjudgement happens. | S135: Two teams meet about a shared project. One uses the phrase the migration throughout. The other team nods, and spends the following fortnight preparing for something different, because in their world that word refers to a different piece of work entirely. | T135: CHECK THE GROUND 1. Before an important conversation, list the three terms you will rely on most. 2. For each, write what you are assuming the other person already knows. 3. Open by checking one of those assumptions out loud. 4. Note which one was wrong. COMMITMENT (if then): "When I start a conversation with someone outside my team, I will check one assumed term before relying on it." | U135: Clear communicator | V135: Curse of Knowledge; Conversational Repair | W135: BK022; BK044 | X135: Claude draft, needs Lindsay review
A136: Stub | B136: 06.10 | C136: Conversational Repair | D136: Integration | E136: Communication & Influence | F136: Communication Principle | G136: Communication Process | H136: Conversation Analysis / Linguistics | U136: Clear communicator | W136: BK044; BK103
A137: Done | B137: 06.11 | C137: Curse of Knowledge | D137: Integration | E137: Communication & Influence | F137: Cognitive Bias | G137: Cognitive Bias | H137: Cognitive Psychology / Communication | I137: Colin Camerer, George Loewenstein and Martin Weber | J137: 1989 | K137: Introductory | L137: Replicated | M137: Once you know something, you cannot imagine not knowing it. | O137: A bias in which knowing something makes it very hard to model the mind of someone who does not. It shows up whenever an expert explains their field: the steps they skip are invisible to them, because the knowledge that fills them is already in place. Demonstrated memorably in Elizabeth Newton's tapping study, where tappers wildly overestimated how often listeners would recognise the tune. | P137: you acquire knowledge -> it becomes automatic -> it stops feeling like knowledge -> you leave it out -> the listener loses the thread where you skipped something without noticing | Q137: "It means experts are bad communicators." Expertise is not the problem; the invisibility of one's own knowledge is. A novice explaining something they half-know is often clearer, not because they know more but because the missing pieces are still visible to them. | R137: ILLUSION OF EXPLANATORY DEPTH. That one is about overestimating how well you understand something yourself. This one is about underestimating how much other people need told. One is a misjudgement of your own knowledge, the other a misjudgement of theirs. | S137: A consultant presents to a new client and uses four abbreviations in the first two minutes without expanding any of them. The room nods along. Afterwards almost no one can describe what was proposed, and the consultant concludes that the client was not paying attention. | T137: NAME WHAT YOU SKIPPED 1. Take something you are about to explain or publish. 2. Underline every term that would need explaining to someone outside your field. 3. For each, ask: did I actually explain it, or assume it? 4. Rewrite the three worst offenders. COMMITMENT (if-then): "When I write something for people outside my work, I will mark every assumed term before I send it." | U137: Clear communicator | V137: Illusion of Explanatory Depth; Feynman Technique (Learning Heuristic) | W137: BK047 | X137: Claude draft, needs Lindsay review
A138: Done | B138: 06.12 | C138: Message Framing | D138: Integration | E138: Communication & Influence | F138: Communication Principle | G138: Communication Principle | H138: Rhetoric / Behavioral Science | I138: Amos Tversky and Daniel Kahneman | J138: 1981 | K138: Introductory | L138: Replicated | M138: The same fact persuades differently depending on how it is framed. | O138: Tversky and Kahneman showed that logically identical information produces different choices depending on presentation. A treatment described as having a ninety per cent survival rate is chosen more often than one with a ten per cent mortality rate. Framing is not a way of adding information. It is a choice about which true description of the same thing you put forward. | P138: one framing is chosen -> it sets what counts as the baseline -> the audience judges gains or losses against that baseline -> the same facts lead to a different decision | Q138: "Framing is a polite word for spin." Spin involves saying things that are not true or hiding things that are. Every statement has a frame, including the plainest one available, so the choice is never between framing and not framing. It is between choosing the frame deliberately and letting it fall where it lands. | R138: ANCHORING. That is the pull of a specific number that was mentioned first, which then drags later estimates toward it. Framing is about which description of a situation is offered. One works through a numeric reference point, the other through the shape of the description. | S138: A subscription team tests two versions of the same price. One reads twelve pounds a month, the other reads under forty pence a day. The cost is identical and both are accurate. The second converts markedly better, and nobody involved said anything untrue. | T138: TWO TRUE FRAMES 1. Take something you need to communicate this week. 2. Write it in the frame that comes naturally. 3. Write a second version, equally true, from the opposite direction. 4. Choose deliberately, and note why. COMMITMENT (if then): "When I write anything meant to persuade, I will draft a second equally true framing before choosing." | U138: Clear communicator; Manipulation proof | V138: Anchoring; Loss Aversion | W138: BK047; BK061 | X138: Claude draft, needs Lindsay review
A139: Stub | B139: 06.13 | C139: Narrative Transportation | D139: Discovery | E139: Communication & Influence | F139: Psychological Effect | G139: Psychological Effect | H139: Narrative Psychology / Communication | U139: Clear communicator; Manipulation proof | W139: BK047; BK073
A140: Done | B140: 06.14 | C140: Ethos, Pathos & Logos | D140: Integration | E140: Communication & Influence | F140: Influence Principle | G140: Rhetorical Framework | H140: Classical Rhetoric | I140: Aristotle | J140: c. 350 BCE | K140: Introductory | L140: Philosophical | M140: Persuasion rests on character, feeling and reasoning together. | O140: Aristotle's account of the three available means of persuasion: ethos, the credibility of the speaker, pathos, the emotional state of the audience, and logos, the reasoning of the argument itself. His point was not that all three are equally weighted in every case, but that an argument relying on only one of them is doing a third of the available work. | P140: argument rests on reasoning alone -> the audience has no reason to trust the speaker and no stake in the outcome -> sound logic persuades nobody all three are present -> credibility makes it worth hearing, feeling makes it matter, reasoning makes it hold | Q140: "Ethos, pathos and logos are three styles, and you pick one." They are not alternatives. They are three things present in every act of persuasion, including when you neglect them. A speech with no attention to ethos still conveys an impression of its speaker, usually a worse one. | R140: ELABORATION LIKELIHOOD MODEL. That is a modern account of when audiences scrutinise an argument closely and when they go on surface cues instead. Aristotle's three are the materials of persuasion; the model is about the conditions under which each gets weight. | S140: A researcher presents a genuinely strong case for a funding change. The reasoning is airtight. She does not mention that she ran the pilot herself, and she never says what happens to the families affected if nothing changes. The committee finds no fault with the argument and does not act on it. | T140: THE MISSING THIRD 1. Take something you need to argue for. 2. Mark which of the three your draft leans on most. 3. Identify the one you have neglected entirely. 4. Add one sentence that supplies it, and no more. COMMITMENT (if then): "When I finish a persuasive draft, I will find the one of the three I neglected and add a single sentence for it." | U140: Clear communicator | V140: Elaboration Likelihood Model; Message Framing | W140: BK047 | X140: Claude draft, needs Lindsay review
A141: Stub | B141: 06.15 | C141: Reciprocity | D141: Integration | E141: Communication & Influence | F141: Influence Principle | G141: Influence Principle | H141: Social Psychology / Persuasion | U141: Manipulation proof; Clear communicator | W141: BK039
A142: Stub | B142: 06.16 | C142: Commitment & Consistency | D142: Integration | E142: Communication & Influence | F142: Influence Principle | G142: Influence Principle | H142: Social Psychology / Persuasion | U142: Manipulation proof; Self-authoring | W142: BK039
A143: Stub | B143: 06.17 | C143: Illusory Truth Effect | D143: Integration | E143: Communication & Influence | F143: Psychological Effect | G143: Psychological Effect | H143: Cognitive Psychology / Persuasion | U143: Manipulation proof; Clear thinker | W143: BK047; BK121
A144: Stub | B144: 06.18 | C144: Motte-and-Bailey Fallacy | D144: Integration | E144: Communication & Influence | F144: Fallacy | G144: Fallacy | H144: Argumentation / Rhetoric | U144: Clear thinker; Manipulation proof | W144: BK130
A145: Stub | B145: 06.19 | C145: Loaded Question Fallacy | D145: Integration | E145: Communication & Influence | F145: Fallacy | G145: Fallacy | H145: Argumentation / Rhetoric | U145: Clear thinker; Manipulation proof | W145: BK040
A146: Stub | B146: 06.20 | C146: Argument by Repetition / Ad Nauseam | D146: Integration | E146: Communication & Influence | F146: Fallacy | G146: Fallacy / Rhetorical Tactic | H146: Argumentation / Persuasion | U146: Clear thinker; Manipulation proof | W146: BK121
A147: Stub | B147: 06.21 | C147: Elaboration Likelihood Model | D147: Discovery | E147: Communication & Influence | F147: Influence Principle | G147: Persuasion Theory | H147: Social Psychology / Communication | U147: Manipulation proof; Clear communicator | W147: BK039; BK047
A148: Stub | B148: 06.22 | C148: Inoculation Theory | D148: Integration | E148: Communication & Influence | F148: Influence Principle | G148: Persuasion Theory | H148: Communication / Social Psychology | U148: Manipulation proof; Clear thinker | W148: BK034
A149: Stub | B149: 06.23 | C149: Foot-in-the-Door Effect | D149: Integration | E149: Communication & Influence | F149: Influence Principle | G149: Influence Technique | H149: Social Psychology / Persuasion | U149: Manipulation proof | W149: BK039
A150: Stub | B150: 06.24 | C150: Door-in-the-Face Effect | D150: Integration | E150: Communication & Influence | F150: Influence Principle | G150: Influence Technique | H150: Social Psychology / Persuasion | U150: Manipulation proof | W150: BK039
A151: Done | B151: 06.25 | C151: Nonviolent Communication Framework | D151: Integration | E151: Communication & Influence | F151: Communication Principle | G151: Communication Framework | H151: Conflict Resolution / Communication | I151: Marshall Rosenberg | J151: 1999 | K151: Intermediate | L151: Framework | M151: Separating what happened from how you felt, what you need and what you are asking. | O151: Rosenberg's framework splits a difficult statement into four parts: the observation, stripped of evaluation, the feeling it produced, the need underneath that feeling, and a specific request. Its work is done by the separation itself, since most conflict comes from these four arriving fused into a single accusation. | P151: observation, feeling, need and request arrive fused -> it lands as an accusation -> the other person defends -> nothing is resolved the four are separated -> there is something concrete to respond to -> the conversation is about the request | Q151: "It is a softer, more polite way of complaining." Politeness is not the mechanism and the framework is often more direct than what it replaces, because it requires naming a specific request rather than hinting. A fused accusation delivered gently is still fused. | R151: AFFECT LABELING. That names the feeling and stops there, and it can be applied to the other person's feeling as well as your own. This framework includes naming a feeling as one of four steps, but the step that does the structural work is the specific request at the end. | S151: After a third late delivery, Dan writes to his supplier that he is being treated as unimportant. The supplier replies defending their workload. Nothing changes. What Dan had wanted, and never said, was to be told on the day something would be late rather than finding out himself. | T151: SPLIT IT INTO FOUR 1. Take something you need to raise with someone. 2. Write the observation with every evaluative word removed. 3. Write the feeling it produced, in one word. 4. Write the need underneath it. 5. Write one specific request that someone could say yes or no to. COMMITMENT (if then): "When I need to raise something difficult, I will write the specific request first and build the rest around it." | U151: Clear communicator; Emotionally regulated; High integrity | V151: Affect Labeling; Gottman's Four Horsemen | W151: BK022; BK103 | X151: Claude draft, needs Lindsay review
A152: Stub | B152: 07.01 | C152: Bases of Social Power | D152: Discovery | E152: Power, Strategy & Conflict | F152: Power Framework | G152: Power Framework | H152: Social Psychology / Sociology | U152: Manipulation proof | W152: BK060; BK078
A153: Stub | B153: 07.02 | C153: Power-Dependence Theory | D153: Discovery | E153: Power, Strategy & Conflict | F153: Power Framework | G153: Power Theory | H153: Sociology / Social Exchange Theory | U153: Manipulation proof; Systems literate | W153: BK060; BK078
A154: Stub | B154: 07.03 | C154: Three Types of Legitimate Authority | D154: Discovery | E154: Power, Strategy & Conflict | F154: Power Framework | G154: Power Framework | H154: Sociology / Political Sociology | U154: Manipulation proof | W154: BK060; BK088
A155: Stub | B155: 07.04 | C155: Concentration of Force | D155: Integration | E155: Power, Strategy & Conflict | F155: Strategic Principle | G155: Strategic Principle | H155: Military Strategy | U155: Systems literate; Disciplined | W155: BK056; BK082
A156: Stub | B156: 07.05 | C156: Asymmetric Strategy | D156: Integration | E156: Power, Strategy & Conflict | F156: Strategic Principle | G156: Strategic Principle | H156: Military / Competitive Strategy | U156: Systems literate | W156: BK082; BK084
A157: Stub | B157: 07.06 | C157: Indirect Approach | D157: Integration | E157: Power, Strategy & Conflict | F157: Strategic Principle | G157: Strategic Principle | H157: Military Strategy | U157: Systems literate | W157: BK082; BK084
A158: Stub | B158: 07.07 | C158: OODA Loop | D158: Integration | E158: Power, Strategy & Conflict | F158: Strategic Principle | G158: Strategic Framework | H158: Military Strategy / Decision Science | U158: Systems literate; Disciplined | W158: BK017
A159: Stub | B159: 07.08 | C159: Strategic Positioning (Shih) | D159: Integration | E159: Power, Strategy & Conflict | F159: Strategic Principle | G159: Strategic Principle | H159: Chinese Military Philosophy | U159: Systems literate | W159: BK082
A160: Stub | B160: 07.09 | C160: Strategic Signaling | D160: Integration | E160: Power, Strategy & Conflict | F160: Strategic Principle | G160: Strategic Dynamic | H160: Game Theory / Strategy | U160: Clear communicator; Manipulation proof | W160: BK082; BK108
A161: Stub | B161: 07.10 | C161: Negotiation Leverage | D161: Integration | E161: Power, Strategy & Conflict | F161: Strategic Principle | G161: Strategic Principle | H161: Negotiation / Power Theory | U161: Manipulation proof; Systems literate | W161: BK001; BK108
A162: Stub | B162: 07.11 | C162: BATNA | D162: Integration | E162: Power, Strategy & Conflict | F162: Strategic Principle | G162: Negotiation Concept | H162: Negotiation Theory | U162: Systems literate; Manipulation proof | W162: BK022
A163: Stub | B163: 07.12 | C163: ZOPA | D163: Integration | E163: Power, Strategy & Conflict | F163: Strategic Principle | G163: Negotiation Concept | H163: Negotiation Theory | U163: Systems literate | W163: BK079
A164: Stub | B164: 07.13 | C164: Reservation Point | D164: Integration | E164: Power, Strategy & Conflict | F164: Strategic Principle | G164: Negotiation Concept | H164: Negotiation Theory | U164: Systems literate; Disciplined | W164: BK057
A165: Done | B165: 07.14 | C165: Positions vs. Interests | D165: Integration | E165: Power, Strategy & Conflict | F165: Strategic Principle | G165: Negotiation Principle | H165: Negotiation Theory | I165: Roger Fisher and William Ury | J165: 1981 | K165: Introductory | L165: Framework | M165: What someone demands is rarely the same as what they actually need. | O165: From Fisher and Ury's work on negotiation. A position is the stated demand. An interest is the underlying need the demand is meant to serve. Positions conflict far more often than interests do, which is why negotiations that trade positions tend to deadlock while negotiations that surface interests often find room neither side knew was there. | P165: both sides state positions -> the positions are incompatible -> the only move is splitting the difference both sides surface interests -> the interests often differ rather than conflict -> options appear that satisfy both | Q165: "It means compromising, or meeting in the middle." Meeting in the middle is what you do when you are still trading positions. Finding interests often avoids compromise entirely, because the two parties turn out to want different things rather than the same thing in different amounts. | R165: BATNA. That is your best alternative if no agreement is reached, and it sets the point below which you should walk away. This is about understanding what either side is actually trying to achieve. One defines your floor, the other opens the space above it. | S165: Two departments both insist on owning the new budget line, and neither will move. Eventually someone asks each what they are trying to do with it. One wants to guarantee a hire. The other wants to be able to show the spend in their own reporting. Both turn out to be possible. | T165: FIND THE INTEREST 1. Take a disagreement you are currently stuck in. 2. Write both stated positions. 3. For each, ask: what is this meant to achieve? Keep asking until you reach something that is not itself a demand. 4. Look for an option that serves both answers. COMMITMENT (if then): "When a negotiation deadlocks, I will ask what the other side is trying to achieve before offering any compromise." | U165: Clear communicator; High integrity | V165: BATNA; Negotiation Leverage | W165: BK022 | X165: Claude draft, needs Lindsay review
A166: Stub | B166: 07.15 | C166: Credible Commitment | D166: Integration | E166: Power, Strategy & Conflict | F166: Game-Theory Concept | G166: Game-Theory Concept | H166: Game Theory / Strategy | U166: High integrity; Manipulation proof | W166: BK088; BK108
A167: Stub | B167: 07.16 | C167: Prisoner’s Dilemma | D167: Discovery | E167: Power, Strategy & Conflict | F167: Game-Theory Concept | G167: Game-Theory Model | H167: Game Theory | U167: Systems literate; Manipulation proof | W167: BK088
...

Sheet Sheet

Sheet Vocabulary
A1: Domains | B1: Types | C1: Identities | D1: Difficulty | E1: Tier | F1: Status | G1: Evidence | H1: What it means
A2: Communication & Influence | B2: Archetype | C2: Clear thinker | D2: Introductory | E2: Discovery | F2: Stub | G2: Replicated | H2: A robust empirical finding that holds up across independent studies
A3: Creativity, Craft & Mastery | B3: Attachment Pattern | C3: Disciplined | D3: Intermediate | E3: Integration | F3: Drafted | G3: Supported | H3: Real research behind it, but less settled or narrower than replicated
A4: Decisions & Risk | B4: Behavioural Principle | C4: Clear communicator | D4: Advanced | F4: In review | G4: Contested | H4: Widely used and widely taught, but the evidence is disputed
A5: Human Nature & Social Behaviour | B5: Cognitive Bias | C5: Emotionally regulated | F5: Done | G5: Framework | H5: A way of organising thinking. Useful or not, rather than true or false
A6: Learning, Memory & Attention | B6: Communication Principle | C6: Manipulation proof | G6: Philosophical | H6: An argument or position, not an empirical claim
A7: Meaning, Ethics & Philosophy | B7: Creativity Concept | C7: High integrity | G7: Traditional | H7: From a wisdom, mythic or religious tradition
A8: Myth, Symbol & Spiritual Traditions | B8: Decision Model | C8: Creatively unblocked
A9: Power, Strategy & Conflict | B9: Defense Mechanism | C9: Self-authoring
A10: Reasoning & Sensemaking | B10: Economic Concept | C10: Sound judgement
A11: Relationships & Attraction | B11: Ethical Principle | C11: Systems literate
A12: Self-Knowledge & Behaviour | B12: Expertise Concept
A13: Society, Culture & Systems | B13: Fallacy
B14: Game-Theory Concept
B15: Heuristic
B16: Influence Principle
B17: Jungian Concept
B18: Learning Principle
B19: Mental Model
B20: Motivation Theory
B21: Mythic Concept
B22: Paradox
B23: Philosophical Principle
B24: Power Framework
B25: Psychological Effect
... B32: Practice
A34: Domains are your existing twelve, straight from the live site, at 25 concepts each. Do not add a thirteenth without deciding what it does to that balance. Types were 130+ distinct strings in the live data ('Psychological Effect' vs 'Psychological Effect / Paradox' vs 'Psychological Concept'). They are consolidated here to 29. Each concept's original string is preserved in the Legacy Type column on the Concepts sheet, so nothing is lost, but the Type column is what the site should use. Tradition is deliberately NOT validated: the live data has 197 distinct values across 300 concepts. Cleaning that up is its own pass, and it does not block anything.

Sheet Books
A1: Book ID | B1: Title | C1: Author | D1: Year | E1: Summary status | F1: One-line take | G1: Concepts linked | H1: Notes
A2: BK001 | B2: 48 Laws of Power | C2: Robert Greene | G2: =COUNTIF(Concepts!$U$2:$U$400,"*"&$A2&"*") -> 0
A3: BK002 | B3: A Guide to the Good Life | C3: William B. Irvine | G3: =COUNTIF(Concepts!$U$2:$U$400,"*"&$A3&"*") -> 0
A4: BK003 | B4: A History of Western Philosophy | C4: Bertrand Russell | G4: =COUNTIF(Concepts!$U$2:$U$400,"*"&$A4&"*") -> 0
A5: BK004 | B5: A Mind for Numbers | C5: Barbara Oakley | D5: 2014 | G5: =COUNTIF(Concepts!$U$2:$U$400,"*"&$A5&"*") -> 0
A6: BK005 | B6: Ad Hominem Arguments | C6: Douglas Walton | D6: 1998 | G6: =COUNTIF(Concepts!$U$2:$U$400,"*"&$A6&"*") -> 0
A7: BK006 | B7: Anatomy of Love | C7: Helen Fisher | G7: =COUNTIF(Concepts!$U$2:$U$400,"*"&$A7&"*") -> 0
A8: BK007 | B8: Antifragile | C8: Nassim Nicholas Taleb | G8: =COUNTIF(Concepts!$U$2:$U$400,"*"&$A8&"*") -> 0
A9: BK008 | B9: Appeal to Expert Opinion | C9: Douglas Walton | D9: 1997 | G9: =COUNTIF(Concepts!$U$2:$U$400,"*"&$A9&"*") -> 0
A10: BK009 | B10: Applied Economics | C10: Thomas Sowell | G10: =COUNTIF(Concepts!$U$2:$U$400,"*"&$A10&"*") -> 0
A11: BK010 | B11: Arguments from Ignorance | C11: Douglas Walton | D11: 1996 | G11: =COUNTIF(Concepts!$U$2:$U$400,"*"&$A11&"*") -> 0
A12: BK011 | B12: Asking the Right Questions | C12: M. Neil Browne & Stuart M. Keeley | D12: 1981 | G12: =COUNTIF(Concepts!$U$2:$U$400,"*"&$A12&"*") -> 0
A13: BK012 | B13: Atomic Habits | C13: James Clear | G13: =COUNTIF(Concepts!$U$2:$U$400,"*"&$A13&"*") -> 0
A14: BK013 | B14: Attached | C14: Amir Levine & Rachel Heller | G14: =COUNTIF(Concepts!$U$2:$U$400,"*"&$A14&"*") -> 0
A15: BK014 | B15: Attacking Faulty Reasoning | C15: T. Edward Damer | D15: 1980 | G15: =COUNTIF(Concepts!$U$2:$U$400,"*"&$A15&"*") -> 0
A16: BK015 | B16: Begging the Question | C16: Douglas Walton | D16: 1991 | G16: =COUNTIF(Concepts!$U$2:$U$400,"*"&$A16&"*") -> 0
A17: BK016 | B17: Big Magic | C17: Elizabeth Gilbert | G17: =COUNTIF(Concepts!$U$2:$U$400,"*"&$A17&"*") -> 0
A18: BK017 | B18: Boyd: The Fighter Pilot Who Changed the Art of War | C18: Robert Coram | D18: 2002 | G18: =COUNTIF(Concepts!$U$2:$U$400,"*"&$A18&"*") -> 0
A19: BK018 | B19: Captivate | C19: Vanessa Van Edwards | G19: =COUNTIF(Concepts!$U$2:$U$400,"*"&$A19&"*") -> 0
A20: BK019 | B20: Chatter | C20: Ethan Kross | D20: 2021 | G20: =COUNTIF(Concepts!$U$2:$U$400,"*"&$A20&"*") -> 0
A21: BK020 | B21: Compelling People | C21: John Neffinger & Matthew Kohut | G21: =COUNTIF(Concepts!$U$2:$U$400,"*"&$A21&"*") -> 0
A22: BK021 | B22: Creative Cognition: Theory, Research, and Applications | C22: Ronald A. Finke, Thomas B. Ward & Steven M. Smith | D22: 1992 | G22: =COUNTIF(Concepts!$U$2:$U$400,"*"&$A22&"*") -> 0
A23: BK022 | B23: Crucial Conversations | C23: Kerry Patterson, Joseph Grenny, Ron McMillan & Al Switzler | G23: =COUNTIF(Concepts!$U$2:$U$400,"*"&$A23&"*") -> 0
A24: BK023 | B24: Curious | C24: Ian Leslie | D24: 2014 | G24: =COUNTIF(Concepts!$U$2:$U$400,"*"&$A24&"*") -> 0
A25: BK024 | B25: Daily Rituals | C25: Mason Currey | G25: =COUNTIF(Concepts!$U$2:$U$400,"*"&$A25&"*") -> 0
A26: BK025 | B26: Debt: The First 5000 Years | C26: David Graeber | G26: =COUNTIF(Concepts!$U$2:$U$400,"*"&$A26&"*") -> 0
A27: BK026 | B27: Decisive | C27: Chip Heath & Dan Heath | G27: =COUNTIF(Concepts!$U$2:$U$400,"*"&$A27&"*") -> 0
A28: BK027 | B28: Deep Work | C28: Cal Newport | D28: 2016 | G28: =COUNTIF(Concepts!$U$2:$U$400,"*"&$A28&"*") -> 0
A29: BK028 | B29: Diffusion of Innovations | C29: Everett M. Rogers | D29: 1962 | G29: =COUNTIF(Concepts!$U$2:$U$400,"*"&$A29&"*") -> 0
A30: BK029 | B30: Discipline Is Destiny | C30: Ryan Holiday | G30: =COUNTIF(Concepts!$U$2:$U$400,"*"&$A30&"*") -> 0
A31: BK030 | B31: Discourse on the Method | C31: René Descartes | D31: 1637 | G31: =COUNTIF(Concepts!$U$2:$U$400,"*"&$A31&"*") -> 0
A32: BK031 | B32: Drive | C32: Daniel H. Pink | G32: =COUNTIF(Concepts!$U$2:$U$400,"*"&$A32&"*") -> 0
A33: BK032 | B33: Emotional Intelligence 2.0 | C33: Travis Bradberry & Jean Greaves | G33: =COUNTIF(Concepts!$U$2:$U$400,"*"&$A33&"*") -> 0
A34: BK033 | B34: Flourish | C34: Martin E. P. Seligman | D34: 2011 | G34: =COUNTIF(Concepts!$U$2:$U$400,"*"&$A34&"*") -> 0
A35: BK034 | B35: Foolproof: Why Misinformation Infects Our Minds and How to Build Immunity | C35: Sander van der Linden | D35: 2023 | G35: =COUNTIF(Concepts!$U$2:$U$400,"*"&$A35&"*") -> 0
A36: BK035 | B36: Freakonomics | C36: Steven D. Levitt & Stephen J. Dubner | G36: =COUNTIF(Concepts!$U$2:$U$400,"*"&$A36&"*") -> 0
A37: BK036 | B37: Give and Take | C37: Adam Grant | D37: 2013 | G37: =COUNTIF(Concepts!$U$2:$U$400,"*"&$A37&"*") -> 0
A38: BK037 | B38: How the World Really Works | C38: Vaclav Smil | G38: =COUNTIF(Concepts!$U$2:$U$400,"*"&$A38&"*") -> 0
A39: BK038 | B39: Ikigai | C39: Héctor García & Francesc Miralles | G39: =COUNTIF(Concepts!$U$2:$U$400,"*"&$A39&"*") -> 0
A40: BK039 | B40: Influence | C40: Robert B. Cialdini | G40: =COUNTIF(Concepts!$U$2:$U$400,"*"&$A40&"*") -> 0
A41: BK040 | B41: Informal Logic: A Pragmatic Approach | C41: Douglas Walton | D41: 1989 | G41: =COUNTIF(Concepts!$U$2:$U$400,"*"&$A41&"*") -> 0
A42: BK041 | B42: Information Rules: A Strategic Guide to the Network Economy | C42: Carl Shapiro & Hal R. Varian | D42: 1998 | G42: =COUNTIF(Concepts!$U$2:$U$400,"*"&$A42&"*") -> 0
A43: BK042 | B43: Lateral Thinking: Creativity Step by Step | C43: Edward de Bono | D43: 1970 | G43: =COUNTIF(Concepts!$U$2:$U$400,"*"&$A43&"*") -> 0
A44: BK043 | B44: Letting Go | C44: David R. Hawkins | G44: =COUNTIF(Concepts!$U$2:$U$400,"*"&$A44&"*") -> 0
A45: BK044 | B45: Linguistics: A Very Short Introduction | C45: P. H. Matthews | G45: =COUNTIF(Concepts!$U$2:$U$400,"*"&$A45&"*") -> 0
A46: BK045 | B46: Logically Fallacious | C46: Bo Bennett | D46: 2012 | G46: =COUNTIF(Concepts!$U$2:$U$400,"*"&$A46&"*") -> 0
A47: BK046 | B47: Love and the Expansion of Self | C47: Arthur Aron & Elaine N. Aron | D47: 1986 | G47: =COUNTIF(Concepts!$U$2:$U$400,"*"&$A47&"*") -> 0
A48: BK047 | B48: Made to Stick | C48: Chip Heath & Dan Heath | G48: =COUNTIF(Concepts!$U$2:$U$400,"*"&$A48&"*") -> 0
A49: BK048 | B49: Make It Stick | C49: Peter C. Brown, Henry L. Roediger III & Mark A. McDaniel | D49: 2014 | G49: =COUNTIF(Concepts!$U$2:$U$400,"*"&$A49&"*") -> 0
G50: =COUNTIF(Concepts!$U$2:$U$400,"*"&$A50&"*") -> 399
A51: BK050 | B51: Man & His Symbols | C51: Carl G. Jung | G51: =COUNTIF(Concepts!$U$2:$U$400,"*"&$A51&"*") -> 0
A52: BK051 | B52: Man’s Search for Meaning | C52: Viktor E. Frankl | D52: 1946 | G52: =COUNTIF(Concepts!$U$2:$U$400,"*"&$A52&"*") -> 0
A53: BK052 | B53: Mastery | C53: Robert Greene | G53: =COUNTIF(Concepts!$U$2:$U$400,"*"&$A53&"*") -> 0
A54: BK053 | B54: Meditations | C54: Marcus Aurelius | G54: =COUNTIF(Concepts!$U$2:$U$400,"*"&$A54&"*") -> 0
A55: BK054 | B55: Mental Representations: A Dual Coding Approach | C55: Allan Paivio | D55: 1986 | G55: =COUNTIF(Concepts!$U$2:$U$400,"*"&$A55&"*") -> 0
A56: BK055 | B56: Models | C56: Mark Manson | G56: =COUNTIF(Concepts!$U$2:$U$400,"*"&$A56&"*") -> 0
A57: BK056 | B57: Napoleon’s Maxims | C57: Napoleon Bonaparte | G57: =COUNTIF(Concepts!$U$2:$U$400,"*"&$A57&"*") -> 0
A58: BK057 | B58: Negotiation Genius | C58: Deepak Malhotra & Max H. Bazerman | D58: 2007 | G58: =COUNTIF(Concepts!$U$2:$U$400,"*"&$A58&"*") -> 0
A59: BK058 | B59: Pathways to Bliss | C59: Joseph Campbell | G59: =COUNTIF(Concepts!$U$2:$U$400,"*"&$A59&"*") -> 0
A60: BK059 | B60: Poor Charlie’s Almanack | C60: Charles T. Munger (ed. Peter D. Kaufman) | D60: 2005 | G60: =COUNTIF(Concepts!$U$2:$U$400,"*"&$A60&"*") -> 0
A61: BK060 | B61: Power - A Social Analysis | C61: Bertrand Russell | G61: =COUNTIF(Concepts!$U$2:$U$400,"*"&$A61&"*") -> 0
A62: BK061 | B62: Predictably Irrational | C62: Dan Ariely | G62: =COUNTIF(Concepts!$U$2:$U$400,"*"&$A62&"*") -> 0
A63: BK062 | B63: Presentation of Self in Everyday Life | C63: Erving Goffman | G63: =COUNTIF(Concepts!$U$2:$U$400,"*"&$A63&"*") -> 0
A64: BK063 | B64: Principles | C64: Ray Dalio | G64: =COUNTIF(Concepts!$U$2:$U$400,"*"&$A64&"*") -> 0
A65: BK064 | B65: Psycho-Cybernetics | C65: Maxwell Maltz | G65: =COUNTIF(Concepts!$U$2:$U$400,"*"&$A65&"*") -> 0
A66: BK065 | B66: Range | C66: David Epstein | G66: =COUNTIF(Concepts!$U$2:$U$400,"*"&$A66&"*") -> 0
A67: BK066 | B67: Reinventing Your Life | C67: Jeffrey E. Young & Janet S. Klosko | G67: =COUNTIF(Concepts!$U$2:$U$400,"*"&$A67&"*") -> 0
A68: BK067 | B68: Science and Sanity | C68: Alfred Korzybski | D68: 1933 | G68: =COUNTIF(Concepts!$U$2:$U$400,"*"&$A68&"*") -> 0
A69: BK068 | B69: Searching for Memory | C69: Daniel L. Schacter | D69: 1996 | G69: =COUNTIF(Concepts!$U$2:$U$400,"*"&$A69&"*") -> 0
A70: BK069 | B70: Six Easy Pieces | C70: Richard P. Feynman | G70: =COUNTIF(Concepts!$U$2:$U$400,"*"&$A70&"*") -> 0
A71: BK070 | B71: Slippery Slope Arguments | C71: Douglas Walton | D71: 1992 | G71: =COUNTIF(Concepts!$U$2:$U$400,"*"&$A71&"*") -> 0
A72: BK071 | B72: Social Mindscapes | C72: Eviatar Zerubavel | G72: =COUNTIF(Concepts!$U$2:$U$400,"*"&$A72&"*") -> 0
A73: BK072 | B73: Stand Out of Our Light | C73: James Williams | D73: 2018 | G73: =COUNTIF(Concepts!$U$2:$U$400,"*"&$A73&"*") -> 0
A74: BK073 | B74: Storyworthy | C74: Matthew Dicks | G74: =COUNTIF(Concepts!$U$2:$U$400,"*"&$A74&"*") -> 0
A75: BK074 | B75: Sweller’s Cognitive Load Theory in Action | C75: Oliver Lovell | D75: 2020 | G75: =COUNTIF(Concepts!$U$2:$U$400,"*"&$A75&"*") -> 0
A76: BK075 | B76: Tao Te Ching | C76: Laozi | G76: =COUNTIF(Concepts!$U$2:$U$400,"*"&$A76&"*") -> 0
A77: BK076 | B77: The Act of Creation | C77: Arthur Koestler | D77: 1964 | G77: =COUNTIF(Concepts!$U$2:$U$400,"*"&$A77&"*") -> 0
A78: BK077 | B78: The All-or-Nothing Marriage | C78: Eli J. Finkel | D78: 2017 | G78: =COUNTIF(Concepts!$U$2:$U$400,"*"&$A78&"*") -> 0
A79: BK078 | B79: The Anatomy of Power | C79: John Kenneth Galbraith | G79: =COUNTIF(Concepts!$U$2:$U$400,"*"&$A79&"*") -> 0
A80: BK079 | B80: The Art and Science of Negotiation | C80: Howard Raiffa | D80: 1982 | G80: =COUNTIF(Concepts!$U$2:$U$400,"*"&$A80&"*") -> 0
A81: BK080 | B81: The Art of Strategy | C81: Avinash K. Dixit & Barry J. Nalebuff | D81: 2008 | G81: =COUNTIF(Concepts!$U$2:$U$400,"*"&$A81&"*") -> 0
A82: BK081 | B82: The Art of Thinking Clearly | C82: Rolf Dobelli | D82: 2013 | G82: =COUNTIF(Concepts!$U$2:$U$400,"*"&$A82&"*") -> 0
A83: BK082 | B83: The Art of War | C83: Sun Tzu | G83: =COUNTIF(Concepts!$U$2:$U$400,"*"&$A83&"*") -> 0
A84: BK083 | B84: The Artist’s Way | C84: Julia Cameron | G84: =COUNTIF(Concepts!$U$2:$U$400,"*"&$A84&"*") -> 0
A85: BK084 | B85: The Book of Five Rings | C85: Miyamoto Musashi | G85: =COUNTIF(Concepts!$U$2:$U$400,"*"&$A85&"*") -> 0
A86: BK085 | B86: The Courage to Be Disliked | C86: Ichiro Kishimi & Fumitake Koga | G86: =COUNTIF(Concepts!$U$2:$U$400,"*"&$A86&"*") -> 0
A87: BK086 | B87: The Creative Act | C87: Rick Rubin | G87: =COUNTIF(Concepts!$U$2:$U$400,"*"&$A87&"*") -> 0
A88: BK087 | B88: The Demon-Haunted World | C88: Carl Sagan | D88: 1995 | G88: =COUNTIF(Concepts!$U$2:$U$400,"*"&$A88&"*") -> 0
A89: BK088 | B89: The Dictator’s Handbook | C89: Bruce Bueno de Mesquita & Alastair Smith | G89: =COUNTIF(Concepts!$U$2:$U$400,"*"&$A89&"*") -> 0
A90: BK089 | B90: The Distracted Mind | C90: Adam Gazzaley & Larry D. Rosen | D90: 2016 | G90: =COUNTIF(Concepts!$U$2:$U$400,"*"&$A90&"*") -> 0
A91: BK090 | B91: The Elephant in the Brain | C91: Kevin Simler & Robin Hanson | G91: =COUNTIF(Concepts!$U$2:$U$400,"*"&$A91&"*") -> 0
A92: BK091 | B92: The Eureka Factor | C92: John Kounios & Mark Beeman | D92: 2015 | G92: =COUNTIF(Concepts!$U$2:$U$400,"*"&$A92&"*") -> 0
A93: BK092 | B93: The Evolution of Cooperation | C93: Robert Axelrod | D93: 1984 | G93: =COUNTIF(Concepts!$U$2:$U$400,"*"&$A93&"*") -> 0
A94: BK093 | B94: The Evolution of Desire | C94: David M. Buss | G94: =COUNTIF(Concepts!$U$2:$U$400,"*"&$A94&"*") -> 0
A95: BK094 | B95: The Farther Reaches of Human Nature | C95: Abraham H. Maslow | G95: =COUNTIF(Concepts!$U$2:$U$400,"*"&$A95&"*") -> 0
A96: BK095 | B96: The Folly of Fools | C96: Robert Trivers | G96: =COUNTIF(Concepts!$U$2:$U$400,"*"&$A96&"*") -> 0
A97: BK096 | B97: The Great Mental Models, Vol. 1: General Thinking Concepts | C97: Shane Parrish & Rhiannon Beaubien | D97: 2019 | G97: =COUNTIF(Concepts!$U$2:$U$400,"*"&$A97&"*") -> 0
A98: BK097 | B98: The Hero With a Thousand Faces | C98: Joseph Campbell | G98: =COUNTIF(Concepts!$U$2:$U$400,"*"&$A98&"*") -> 0
A99: BK098 | B99: The Knowledge Illusion | C99: Steven Sloman & Philip Fernbach | D99: 2017 | G99: =COUNTIF(Concepts!$U$2:$U$400,"*"&$A99&"*") -> 0
A100: BK099 | B100: The Laws of Human Nature | C100: Robert Greene | G100: =COUNTIF(Concepts!$U$2:$U$400,"*"&$A100&"*") -> 0
...

Sheet Identities
A1: Identity | B1: The claim they earn | C1: Folds in | D1: Integration | E1: Discovery | F1: Total | G1: Share of library
A2: Clear thinker | B2: I am a critical thinker | C2: Understands complex ideas; sharp memory | D2: =COUNTIFS(Concepts!$S$2:$S$400,"*"&$A2&"*",Concepts!$D$2:$D$400,"Integration") -> 0 | E2: =COUNTIFS(Concepts!$S$2:$S$400,"*"&$A2&"*",Concepts!$D$2:$D$400,"Discovery") -> 0 | F2: =D2+E2 -> 0 | G2: =IFERROR($F2/COUNTA(Concepts!$C$2:$C$400),0) -> 0
A3: Disciplined | B3: I am disciplined and consistent | C3: Consistency; intentional with my time; habits build my life | D3: =COUNTIFS(Concepts!$S$2:$S$400,"*"&$A3&"*",Concepts!$D$2:$D$400,"Integration") -> 0 | E3: =COUNTIFS(Concepts!$S$2:$S$400,"*"&$A3&"*",Concepts!$D$2:$D$400,"Discovery") -> 0 | F3: =D3+E3 -> 0 | G3: =IFERROR($F3/COUNTA(Concepts!$C$2:$C$400),0) -> 0
A4: Clear communicator | B4: I am a clear communicator | C4: Concise; storytelling; writing; debating | D4: =COUNTIFS(Concepts!$S$2:$S$400,"*"&$A4&"*",Concepts!$D$2:$D$400,"Integration") -> 0 | E4: =COUNTIFS(Concepts!$S$2:$S$400,"*"&$A4&"*",Concepts!$D$2:$D$400,"Discovery") -> 0 | F4: =D4+E4 -> 0 | G4: =IFERROR($F4/COUNTA(Concepts!$C$2:$C$400),0) -> 0
A5: Emotionally regulated | B5: I have a calm nervous system | C5: Emotional regulation; not affected by others; positive self-dialogue | D5: =COUNTIFS(Concepts!$S$2:$S$400,"*"&$A5&"*",Concepts!$D$2:$D$400,"Integration") -> 0 | E5: =COUNTIFS(Concepts!$S$2:$S$400,"*"&$A5&"*",Concepts!$D$2:$D$400,"Discovery") -> 0 | F5: =D5+E5 -> 0 | G5: =IFERROR($F5/COUNTA(Concepts!$C$2:$C$400),0) -> 0
A6: Manipulation proof | B6: I understand human nature | C6: Reads behaviour; resists influence | D6: =COUNTIFS(Concepts!$S$2:$S$400,"*"&$A6&"*",Concepts!$D$2:$D$400,"Integration") -> 0 | E6: =COUNTIFS(Concepts!$S$2:$S$400,"*"&$A6&"*",Concepts!$D$2:$D$400,"Discovery") -> 0 | F6: =D6+E6 -> 0 | G6: =IFERROR($F6/COUNTA(Concepts!$C$2:$C$400),0) -> 0
A7: High integrity | B7: I have integrity with myself and others | C7: Grace with boundaries | D7: =COUNTIFS(Concepts!$S$2:$S$400,"*"&$A7&"*",Concepts!$D$2:$D$400,"Integration") -> 0 | E7: =COUNTIFS(Concepts!$S$2:$S$400,"*"&$A7&"*",Concepts!$D$2:$D$400,"Discovery") -> 0 | F7: =D7+E7 -> 0 | G7: =IFERROR($F7/COUNTA(Concepts!$C$2:$C$400),0) -> 0
A8: Creatively unblocked | B8: I make creativity a priority | C8: No creative blocks | D8: =COUNTIFS(Concepts!$S$2:$S$400,"*"&$A8&"*",Concepts!$D$2:$D$400,"Integration") -> 0 | E8: =COUNTIFS(Concepts!$S$2:$S$400,"*"&$A8&"*",Concepts!$D$2:$D$400,"Discovery") -> 0 | F8: =D8+E8 -> 0 | G8: =IFERROR($F8/COUNTA(Concepts!$C$2:$C$400),0) -> 0
A9: Self-authoring | B9: I don't let my past define my future | C9: Stops self-sabotage | D9: =COUNTIFS(Concepts!$S$2:$S$400,"*"&$A9&"*",Concepts!$D$2:$D$400,"Integration") -> 0 | E9: =COUNTIFS(Concepts!$S$2:$S$400,"*"&$A9&"*",Concepts!$D$2:$D$400,"Discovery") -> 0 | F9: =D9+E9 -> 0 | G9: =IFERROR($F9/COUNTA(Concepts!$C$2:$C$400),0) -> 0
A10: Sound judgement | B10: I decide well under uncertainty | C10: Weighs risk; resists the biases that distort choosing; knows what a number does and does not tell them | D10: =COUNTIFS(Concepts!$T$2:$T$600,"*"&$A10&"*",Concepts!$D$2:$D$600,"Integration") -> 0 | E10: =COUNTIFS(Concepts!$T$2:$T$600,"*"&$A10&"*",Concepts!$D$2:$D$600,"Discovery") -> 0 | F10: =D10+E10 -> 0 | G10: =IFERROR($F10/COUNTA(Concepts!$C$2:$C$600),0) -> 0
A11: Systems literate | B11: I see why things turn out as they do | C11: Reads incentives, institutions and power; understands why good people can produce bad outcomes | D11: =COUNTIFS(Concepts!$T$2:$T$600,"*"&$A11&"*",Concepts!$D$2:$D$600,"Integration") -> 0 | E11: =COUNTIFS(Concepts!$T$2:$T$600,"*"&$A11&"*",Concepts!$D$2:$D$600,"Discovery") -> 0 | F11: =D11+E11 -> 0 | G11: =IFERROR($F11/COUNTA(Concepts!$C$2:$C$600),0) -> 0
A13: Clear thinker was split in three on 4 October. It had grown to 209 concepts, forty three per cent of the library, which meant a user choosing it got almost half of everything weighted toward them while a user on a thin identity got very little. Reasoning and logic stayed as Clear thinker. Decisions under uncertainty became Sound judgement. Incentives, institutions and power became Systems literate. Integration concepts are the expensive ones, because they need a Praxis Exercise written. Discovery concepts are roughly half the work. Watch the Share column as the library grows: if one identity drifts far above the others, users who pick it get a weighted wheel full of material while users on a thin identity get very little. A first slice is a COUNT you choose (say 15 concepts), not a whole identity. Nothing is tagged yet unless you have tagged it, and until a concept carries a tag it can never be surfaced by a goal or weight the wheel. Cut deliberately: 'high self confidence & self worth' names a feeling, not a practice. There is no instance of it a user can log. Test for anything added: can a user point to a specific thing they did, on a specific day, that counts as evidence? Spelling must match the Vocabulary sheet exactly, because matching is literal and a typo fails silently.

Sheet Authoring Guide
A1: PRAXIS concept library
A2: Seeded from the 300 concepts already live on the site. Every row starts as a Stub.
A4: Progress
A5: Concepts in library | B5: =COUNTA(Concepts!$C$2:$C$400) -> 399
A6: Done | B6: =COUNTIF(Concepts!$A$2:$A$400,"Done") -> 60
A7: Drafted or in review | B7: =COUNTIF(Concepts!$A$2:$A$400,"Drafted")+COUNTIF(Concepts!$A$2:$A$400,"In review") -> 0
A8: Still a stub | B8: =COUNTIF(Concepts!$A$2:$A$400,"Stub") -> 339
A9: Tagged to an identity | B9: =COUNTIF(Concepts!$S$2:$S$400,"?*") -> 60
A10: Tier assigned | B10: =COUNTIF(Concepts!$D$2:$D$400,"?*") -> 399
A11: Books in library | B11: =COUNTA(Books!$B$2:$B$300) -> 138
A13: Where to start
A14: Do not author breadth-first | B14: 300 concepts at full depth is well over a hundred hours. Pick ONE identity, complete every concept under it, and you have a shippable vertical slice: a goal a user can set, a weighted wheel, enough scenarios to interleave against.
A15: Step one | B15: Assign Tier and Identity Tags across all 300. Fast, mechanical, and it tells you how big each vertical slice actually is before you commit to one.
A16: Step two | B16: Filter to your chosen identity and author those rows to Done.
A18: The tier test
A19: One question | B19: Can you write an honest if-then commitment for this concept? If yes it is Integration tier and needs a Praxis Exercise. If no it is Discovery tier and must not have one.
A20: Why it matters | B20: Forcing a protocol onto a concept that has none is how a library fills with self-help sludge. Plenty of your Myth, Symbol & Spiritual Traditions entries are Discovery tier, and that is correct.
A22: Field standards
A23: Evidence | B23: How far a reader should trust this as a claim about the world. Replicated, Supported, Contested, Framework, Philosophical or Traditional, spelled exactly as on the Vocabulary sheet. Most of the library is Framework or Philosophical and that is fine. Contested is for ideas that are taught everywhere and whose evidence is genuinely disputed, and the card says so out loud. The export refuses a finished concept with this left blank.
A24: One Sentence | B24: Under 20 words, no jargon. Also the hook line for short-form video, so it has to land spoken aloud.
A25: Story | B25: Optional, and the whole point of a myth. Where a concept arrives as a narrative, tell the narrative here in 150 to 220 words, in paragraphs separated by a blank line, and the site gives it a reading screen of its own before any question. Tell it, do not summarise it: the concrete details are what make it stick. Required for anything typed Mythic Concept or Archetype, and the export refuses those without one. Also worth filling for concepts that are really stories, such as Ship of Theseus, the Trolley Problem and Solomon's Paradox.
A26: Definition | B26: 3-5 sentences. The canonical version, including origin where it sharpens meaning.
A27: Mechanism | B27: Write as an ORDERED CHAIN with -> arrows, not a paragraph. Map It is generated by splitting at the arrows, so prose here means no exercise.
A28: Common Misconception | B28: The degraded internet version stated plainly, then what is wrong with it. Feeds the Distinguish rung, the Teach It rubric and the video hook.
A29: Nearest Neighbour | B29: Start with the concept's name in CAPITALS followed by a full stop, then the real difference. The site rewrites that opening into a sentence, so a comma inside the capitalised name breaks it. Supplies the hardest distractor free.
A30: Discriminate Scenario | B30: 40-70 words. A situation where the concept operates, never naming it. Becomes the Spot rung and joins the shared interleaving pool.
A31: Praxis Exercise | B31: Integration tier only. Recognise -> Use -> Act, ending in an if-then commitment with a verb and a timeframe.
A32: Identity Tags | B32: 1-3 from the Identities sheet, semicolon separated, spelled exactly.
A33: Related Concepts | B33: Semicolon separated, by Praxis ID or Canonical Name. Write the link once from either side and the export mirrors it.
A34: Book IDs | B34: Semicolon separated, from the Books sheet. Never a title. Pre-filled from the live site's reference lists.
A36: Publishing
A37: The loop | B37: Edit in Google Sheets -> download as .xlsx -> upload into content/ on GitHub -> the Export content library workflow runs itself -> publish from GoDaddy.
A38: It will refuse | B38: if a Done row is missing a required field for its tier, a Domain or Type is off-vocabulary, an Identity Tag is misspelled, a Book ID does not exist, a Discovery row carries an exercise, or a Discriminate Scenario names its own concept.
A39: Only Done rows ship | B39: Stubs and drafts never reach the site, so you can author in the open.
